{
    "kind": "customsearch#search",
    "url": {
        "type": "application/json",
        "template": "https://www.googleapis.com/customsearch/v1?q={searchTerms}&num={count?}&start={startIndex?}&lr={language?}&safe={safe?}&cx={cx?}&sort={sort?}&filter={filter?}&gl={gl?}&cr={cr?}&googlehost={googleHost?}&c2coff={disableCnTwTranslation?}&hq={hq?}&hl={hl?}&siteSearch={siteSearch?}&siteSearchFilter={siteSearchFilter?}&exactTerms={exactTerms?}&excludeTerms={excludeTerms?}&linkSite={linkSite?}&orTerms={orTerms?}&dateRestrict={dateRestrict?}&lowRange={lowRange?}&highRange={highRange?}&searchType={searchType}&fileType={fileType?}&rights={rights?}&imgSize={imgSize?}&imgType={imgType?}&imgColorType={imgColorType?}&imgDominantColor={imgDominantColor?}&alt=json"
    },
    "queries": {
        "request": [
            {
                "title": "Google Custom Search - evidence linking video of young girls to Jeffrey Epstein's island",
                "totalResults": "11300",
                "searchTerms": "evidence linking video of young girls to Jeffrey Epstein's island",
                "count": 10,
                "startIndex": 1,
                "inputEncoding": "utf8",
                "outputEncoding": "utf8",
                "safe": "off",
                "cx": "73d45d507c0b2430e"
            }
        ],
        "nextPage": [
            {
                "title": "Google Custom Search - evidence linking video of young girls to Jeffrey Epstein's island",
                "totalResults": "11300",
                "searchTerms": "evidence linking video of young girls to Jeffrey Epstein's island",
                "count": 10,
                "startIndex": 11,
                "inputEncoding": "utf8",
                "outputEncoding": "utf8",
                "safe": "off",
                "cx": "73d45d507c0b2430e"
            }
        ]
    },
    "context": {
        "title": "DogeNet Search"
    },
    "searchInformation": {
        "searchTime": 0.193669,
        "formattedSearchTime": "0.19",
        "totalResults": "11300",
        "formattedTotalResults": "11,300"
    },
    "items": [
        {
            "evidence0": {
                "kind": "customsearch#result",
                "title": "Why conspiracy theories about Jeffrey Epstein keep flourishing : NPR",
                "htmlTitle": "Why conspiracy theories about <b>Jeffrey</b> Epstein keep flourishing : NPR",
                "link": "https://www.npr.org/2022/09/08/1121525125/heres-why-conspiracy-theories-about-jeffrey-epstein-keep-flourishing",
                "displayLink": "www.npr.org",
                "snippet": "Sep 8, 2022 ... Each detail of Epstein's real, elaborate predation of young girls serves as a factual toehold for believers of the Pizzagate and QAnon\u00a0...",
                "htmlSnippet": "Sep 8, 2022 <b>...</b> Each detail of <b>Epstein&#39;s</b> real, elaborate predation of <b>young girls</b> serves as a factual toehold for believers of the Pizzagate and QAnon&nbsp;...",
                "formattedUrl": "https://www.npr.org/.../heres-why-conspiracy-theories-about-jeffrey-epstein...",
                "htmlFormattedUrl": "https://www.npr.org/.../heres-why-conspiracy-theories-about-<b>jeffrey</b>-epstein...",
                "pagemap": {
                    "cse_thumbnail": [
                        {
                            "src": "https://encrypted-tbn0.gstatic.com/images?q=tbn:ANd9GcTeWp-hN69Ld8W-G0K2qp8kW1E5EspiSI3hxq9UtI2VA_peeFjI7Ifziro&s",
                            "width": "300",
                            "height": "168"
                        }
                    ],
                    "speakablespecification": [
                        {
                            "cssselector": "[data-is-speakable]"
                        }
                    ],
                    "metatags": [
                        {
                            "date": "2022-09-08",
                            "apple-itunes-app": "app-id=324906251, app-argument=https://www.npr.org/2022/09/08/1121525125/heres-why-conspiracy-theories-about-jeffrey-epstein-keep-flourishing",
                            "og:image": "https://media.npr.org/assets/img/2022/09/07/gettyimages-1236890328_wide-3e0fa19f233d599afbaf27c08577e7c0b4126573.jpg?s=1400&c=100&f=jpeg",
                            "og:type": "article",
                            "twitter:card": "summary_large_image",
                            "twitter:title": "Here's why conspiracy theories about Jeffrey Epstein keep flourishing",
                            "og:site_name": "NPR",
                            "cxenseparse:pageclass": "article",
                            "twitter:domain": "npr.org",
                            "cxenseparse:publishtime": "2022-09-08T05:00:05-04:00",
                            "og:title": "Here's why conspiracy theories about Jeffrey Epstein keep flourishing",
                            "rating": "General",
                            "og:description": "Wealthy and powerful sex offender Jeffrey Epstein has been dead for three years, but members of the far-right keep invoking him in conspiracy theories to smear their opponents.",
                            "fb:pages": "10643211755",
                            "twitter:image:src": "https://media.npr.org/assets/img/2022/09/07/gettyimages-1236890328_wide-3e0fa19f233d599afbaf27c08577e7c0b4126573.jpg?s=1400&c=100&f=jpeg",
                            "fb:app_id": "138837436154588",
                            "cxenseparse:author": "Lisa Hagen",
                            "twitter:site": "@NPR",
                            "viewport": "width=device-width, initial-scale=1, shrink-to-fit=no",
                            "article:content_tier": "free",
                            "og:url": "https://www.npr.org/2022/09/08/1121525125/heres-why-conspiracy-theories-about-jeffrey-epstein-keep-flourishing",
                            "article:opinion": "false"
                        }
                    ],
                    "cse_image": [
                        {
                            "src": "https://media.npr.org/assets/img/2022/09/07/gettyimages-1236890328_wide-3e0fa19f233d599afbaf27c08577e7c0b4126573.jpg?s=1400&c=100&f=jpeg"
                        }
                    ]
                },
                "website_content": {
                    "content": "Why conspiracy theories about Jeffrey Epstein keep flourishing : NPR =============== Accessibility links * * ! ****Play Live Radio**** * **Hourly News** * **Listen Live** * **Playlist** * Open Navigation Menu * ] * * * * Close Navigation Menu * * Expand/collapse submenu for News * * * * * * * * * Expand/collapse submenu for Culture * * * * * * * * * * Expand/collapse submenu for Music * * * * * * Expand/collapse submenu for Podcasts & Shows Daily * Morning Edition] * Weekend Edition Saturday] * Weekend Edition Sunday] * All Things Considered] * Fresh Air] * Up First] Featured * The NPR Politics Podcast] * Throughline] * Trump's Trials] * Wild Card with Rachel Martin] * * * * * * !] * * * * * * * * * * * **Why conspiracy theories about Jeffrey Epstein keep flourishing** **Wealthy and powerful sex offender Jeffrey Epstein has been dead for three years, but members of the far-right keep invoking him in conspiracy theories to smear their opponents.** Here's why conspiracy theories about Jeffrey Epstein keep flourishing ===================================================================== September 8, 20225:00 AM ET By ! Enlarge this image Protesters with signs linking the late Jeffrey Epstein to conspiracy theories at the sex trafficking trial of his accomplice, Ghislaine Maxwell , in November 2021 in New York City. **David Dee Delgado/Getty Images** ****hide caption**** ****toggle caption**** David Dee Delgado/Getty Images ! Protesters with signs linking the late Jeffrey Epstein to conspiracy theories at the sex trafficking trial of his accomplice, Ghislaine Maxwell , in November 2021 in New York City. David Dee Delgado/Getty Images , but his ghost still wanders the dark halls of the internet. In life, Epstein was a secretive financier, arrested for a series of sexual crimes with ... [Content truncated]",
                    "content_tokens": 300
                },
                "website_quality_evaluation": {
                    "website_qualityScore": 9,
                    "justification": "NPR is known for its commitment to high-quality journalism, providing in-depth reporting and analysis. It adheres to strict editorial standards and practices. The network has a long history of reliable news coverage and fact-checking, making it a trustworthy source for news and information. However, as with any organization, it may occasionally exhibit biases based on story selection."
                },
                "ContentScore": {
                    "NewnessScore": 9,
                    "Newness Justification": "The source is from September 2022, which is relatively recent compared to the current date of July 2024. This indicates a high degree of currency concerning ongoing discussions about Jeffrey Epstein.",
                    "RelevanceScore": 5,
                    "Relevance Justification": "This article discusses conspiracy theories related to Epstein's predation of young girls but does not directly address the specific claim about the video linking it to Epstein's island."
                }
            }
        },
        {
            "evidence1": {
                "kind": "customsearch#result",
                "title": "Discredited claims about Clinton, Trump mentioned in latest batch of ...",
                "htmlTitle": "Discredited claims about Clinton, Trump mentioned in latest batch of ...",
                "link": "https://abcnews.go.com/US/new-round-jeffrey-epstein-court-documents-unsealed/story?id=106174129",
                "displayLink": "abcnews.go.com",
                "snippet": "Jan 9, 2024 ... ... Epstein's sex trafficking of young women and girls. Her appeal will be heard in March. Jeffrey Epstein's ... Epstein's private island in a\u00a0...",
                "htmlSnippet": "Jan 9, 2024 <b>...</b> ... Epstein&#39;s sex trafficking of <b>young</b> women and <b>girls</b>. Her appeal will be heard in March. <b>Jeffrey Epstein&#39;s</b> ... Epstein&#39;s private <b>island</b> in a&nbsp;...",
                "formattedUrl": "https://abcnews.go.com/US/new-round-jeffrey-epstein-court.../story?id...",
                "htmlFormattedUrl": "https://abcnews.go.com/US/new-round-<b>jeffrey</b>-epstein-court.../story?id...",
                "pagemap": {
                    "cse_thumbnail": [
                        {
                            "src": "https://encrypted-tbn0.gstatic.com/images?q=tbn:ANd9GcQOs2HyEyjhfEyVSWArSGcny4PL09MBTwR_sg5zHPDp0cahLXcZIj_JnVwt&s",
                            "width": "300",
                            "height": "168"
                        }
                    ],
                    "metatags": [
                        {
                            "og:image": "https://i.abcnewsfe.com/a/62e523b1-5c89-4f82-80f7-06a7f8b18fd4/Jeffrey-Epstein-ap-gmh-240104_1704386953481_hpMain_16x9.jpg?w=1600",
                            "twitter:app:url:iphone": "abcnewsiphone://link/prism-story,106174129",
                            "twitter:app:id:googleplay": "com.abc.abcnews",
                            "copyright": "2024 ABC News",
                            "twitter:card": "summary_large_image",
                            "og:site_name": "ABC News",
                            "twitter:url": "https://abcnews.go.com/US/new-round-jeffrey-epstein-court-documents-unsealed/story?id=106174129",
                            "twitter:app:url:ipad": "abcnewsipad://link/prism-story,106174129",
                            "twitter:image:height": "360",
                            "al:ipad:app_store_id": "380520716",
                            "twitter:app:name:googleplay": "ABC News",
                            "twitter:app:id:iphone": "300255638",
                            "og:description": "The records are part of a defamation lawsuit brought by Virginia Giuffre, an alleged victim of Epstein, against his longtime companion Ghislaine Maxwell.",
                            "twitter:creator": "ABC News",
                            "twitter:image": "https://i.abcnewsfe.com/a/62e523b1-5c89-4f82-80f7-06a7f8b18fd4/Jeffrey-Epstein-ap-gmh-240104_1704386953481_hpMain_16x9.jpg?w=1600",
                            "lastpublisheddate": "2024-01-09T13:46:26Z",
                            "al:iphone:app_name": "ABC News - Breaking US & World News",
                            "twitter:site": "@ABC",
                            "twitter:image:width": "640",
                            "fb:admins": "704409894",
                            "article:content_tier": "free",
                            "fb_title": "Discredited claims about Clinton, Trump mentioned in latest batch of Epstein docs",
                            "og:type": "article",
                            "twitter:title": "Discredited claims about Clinton, Trump mentioned in latest batch of Epstein docs",
                            "author": "ABC News",
                            "og:title": "Discredited claims about Clinton, Trump mentioned in latest batch of Epstein docs",
                            "twitter:app:id:ipad": "306934135",
                            "fb:pages": "86680728811",
                            "al:iphone:url": "abcnewsiphone://link/prism-story,106174129",
                            "fb:app_id": "4942312939",
                            "twitter:app:url:googleplay": "https://abcnews.go.com/US/new-round-jeffrey-epstein-court-documents-unsealed/story?id=106174129",
                            "al:ipad:url": "abcnewsipad://link/prism-story,106174129",
                            "twitter:app:name:ipad": "ABC News",
                            "viewport": "initial-scale=1.0, user-scalable=yes",
                            "twitter:description": "The records are part of a defamation lawsuit brought by Virginia Giuffre, an alleged victim of Epstein, against his longtime companion Ghislaine Maxwell.",
                            "al:iphone:app_store_id": "300255638",
                            "og:locale": "en_US",
                            "og:url": "https://abcnews.go.com/US/new-round-jeffrey-epstein-court-documents-unsealed/story?id=106174129",
                            "twitter:app:name:iphone": "ABC News",
                            "article:opinion": "false"
                        }
                    ],
                    "cse_image": [
                        {
                            "src": "https://i.abcnewsfe.com/a/62e523b1-5c89-4f82-80f7-06a7f8b18fd4/Jeffrey-Epstein-ap-gmh-240104_1704386953481_hpMain_16x9.jpg?w=1600"
                        }
                    ]
                },
                "website_content": {
                    "content": "A new round of from a lawsuit related to the late sex offender Jeffrey Epstein were released Monday, which include photos from an accuser as well as an exhibit that mentions discredited allegations she made about Bill Clinton, Donald Trump, Prince Andrew and Richard Branson. At least 17 documents were unsealed. have been released since Wednesday. The records are part of a defamation lawsuit brought by Virginia Giuffre, an alleged victim of Epstein, against his longtime companion Ghislaine Maxwell that the two settled in 2017. Epstein died by suicide in a Manhattan jail while awaiting trial on federal sex trafficking charges. Maxwell is serving a 20-year prison sentence after she was convicted in 2021 of aiding Epstein's sex trafficking of young women and girls. Her appeal will be heard in March. ! Jeffrey Epstein's longtime companion Ghislaine Maxwell is seen on E... United States District Court Southern District of New York The documents unsealed Monday include several photographs produced by Sarah Ransome, who filed a lawsuit against Epstein, Maxwell and other alleged co-conspirators in 2017 under the pseudonym \"Jane Doe 43.\" Ransome was also involved in the Giuffre case as a witness. She was deposed and provided dozens of photographs showing Epstein, Maxwell, herself and other young women on Epstein's private island. According to another unsealed filing, Ransome testified that some of the pictures were taken by Jean Luc Brunel, a French model scout and associate of Epstein, and given to her by him. ! Sarah Ransome, who filed a lawsuit against Jeffrey Epstein, Ghislain... United States District Court Southern District of New York Brunel in his prison cell in February 2022 while awaiting trial on charges of rape of underage girls and sexual harassment -- a crime in France. Brunel had maintained he was innocent. Several of the photographs ... [Content truncated]",
                    "content_tokens": 300
                },
                "website_quality_evaluation": {
                    "website_qualityScore": 8,
                    "justification": "ABC News is a well-established news organization that provides a variety of accurate news reports and investigative journalism. While it has a reputable stance in the media landscape, it is sometimes critiqued for sensationalism, especially in breaking news coverage. Nonetheless, its overall reliability and efforts in fact-checking score it highly."
                },
                "ContentScore": {
                    "NewnessScore": 7,
                    "Newness Justification": "The article was published on January 9, 2024, making it quite recent and relevant to current discussions on Jeffrey Epstein's activities.",
                    "RelevanceScore": 6,
                    "Relevance Justification": "While it mentions Epstein\u2019s trafficking and his private island, it does not directly link to the specific video in question, so the relevance is moderate."
                }
            }
        },
        {
            "evidence2": {
                "kind": "customsearch#result",
                "title": "What we know about recent claims linking Bill Clinton ... - PolitiFact",
                "htmlTitle": "What we know about recent claims linking Bill Clinton ... - PolitiFact",
                "link": "https://www.politifact.com/article/2020/aug/18/what-we-know-about-recent-claims-linking-bill-clin/",
                "displayLink": "www.politifact.com",
                "snippet": "Aug 18, 2020 ... Newsweek, Bill Clinton went to Jeffrey Epstein's island with 2 'young girls,' Virginia Giuffre says, July 30, 2020. The Daily Beast, Epstein\u00a0...",
                "htmlSnippet": "Aug 18, 2020 <b>...</b> Newsweek, Bill Clinton went to <b>Jeffrey Epstein&#39;s island</b> with 2 &#39;<b>young girls</b>,&#39; Virginia Giuffre says, July 30, 2020. The Daily Beast, Epstein&nbsp;...",
                "formattedUrl": "https://www.politifact.com/.../what-we-know-about-recent-claims-linking-bi...",
                "htmlFormattedUrl": "https://www.politifact.com/.../what-we-know-about-recent-claims-<b>linking</b>-bi...",
                "pagemap": {
                    "cse_thumbnail": [
                        {
                            "src": "https://encrypted-tbn0.gstatic.com/images?q=tbn:ANd9GcSnY17GosZdQWDGZqi6LPi20tCkkry6Dl8ylhs6R7mMBGLEUfW3dIbU7tPK&s",
                            "width": "297",
                            "height": "169"
                        }
                    ],
                    "metatags": [
                        {
                            "og:image": "https://static.politifact.com/CACHE/images/politifact/photos/AP_18156625737127/f37149c358756d20169eee4f8a63feee.jpg",
                            "og:type": "website",
                            "og:image:width": "600",
                            "twitter:card": "summary",
                            "twitter:title": "What we know about recent claims linking Bill Clinton and Jeffrey Epstein",
                            "og:site_name": "@politifact",
                            "twitter:url": "https://www.politifact.com/article/2020/aug/18/what-we-know-about-recent-claims-linking-bill-clin/",
                            "author": "Ciara O'Rourke",
                            "og:title": "What we know about recent claims linking Bill Clinton and Jeffrey Epstein",
                            "og:image:height": "600",
                            "fb:pages": "61308923432",
                            "og:description": "With former President Bill Clinton slated to speak on the second night of the Democratic National Convention, some Ameri",
                            "og:image:secure_url": "https://static.politifact.com/CACHE/images/politifact/photos/AP_18156625737127/f37149c358756d20169eee4f8a63feee.jpg",
                            "twitter:image": "https://static.politifact.com/CACHE/images/politifact/photos/AP_18156625737127/f37149c358756d20169eee4f8a63feee.jpg",
                            "facebook-domain-verification": "vrxxsw8mwnf2pxgnwxvgsn4g93w3vm",
                            "twitter:site": "PolitiFact",
                            "viewport": "width=device-width, initial-scale=1",
                            "twitter:description": "With former President Bill Clinton slated to speak on the second night of the Democratic National Convention, some Ameri",
                            "publisher": "PolitiFact",
                            "fb:admins": "750116788",
                            "twitter:username": "PolitiFact",
                            "og:url": "https://www.politifact.com/article/2020/aug/18/what-we-know-about-recent-claims-linking-bill-clin/"
                        }
                    ],
                    "cse_image": [
                        {
                            "src": "https://static.politifact.com/CACHE/images/politifact/photos/AP_18156625737127/f37149c358756d20169eee4f8a63feee.jpg"
                        }
                    ]
                },
                "website_content": {
                    "content": "PolitiFact | What we know about recent claims linking Bill Clinton and Jeffrey Epstein =============== State Editions * * * * * * * * * * * Issues * **** * * * * * * * * * * * * People * * * * * * Media * * * * * * Campaigns * Truth-o-Meter * * * * * * Promises * * * * About Us * * * * * * * * #### Follow us The Facts Newsletter Sign up **** ### Get PolitiFact in your inbox. * Weekly Email Newsletter * Daily Email Newsletter Your Email Address Sign Up What we know about recent claims linking Bill Clinton and Jeffrey Epstein ========================================================================= * ! ! Former President Bill Clinton was slated to address the Democratic National Convention on Aug. 18, 2020. (AP) ] By August 18, 2020 With former President Bill Clinton slated to speak on the second night of the Democratic National Convention, some Americans were incredulous. \"Anyone wanna explain to me how Bill Clinton who was photographed with the young women raped on pedophile island and on a flight log 26 times is the honored guest speaker at the 2020 DNC? No really PLEASE do explain,\" . It was flagged as part of Facebook\u2019s efforts to combat false news and misinformation on its News Feed. (Read more about our .) A spokesperson for Clinton did not immediately respond to our questions about the Facebook post. Jeffrey Epstein, the late financier and convicted sex offender, and other high-profile public figures, such as President Donald Trump. Clinton has denied he had a close relationship with Epstein, and after Epstein was newly accused in 2019 of sexually abusing children for more than a decade, a spokesman for the former president : ... [Content truncated]",
                    "content_tokens": 300
                },
                "website_quality_evaluation": {
                    "website_qualityScore": 10,
                    "justification": "Politifact is dedicated to fact-checking political claims and is highly respected for its rigorous methodology. It has won a Pulitzer Prize for its work and consistently demonstrates a commitment to transparency and accuracy. It is an essential resource for verifying claims and fact-checking news."
                },
                "ContentScore": {
                    "NewnessScore": 4,
                    "Newness Justification": "The article from August 2020 is dated and does not reflect the most recent developments regarding Epstein, significantly reducing its currency.",
                    "RelevanceScore": 3,
                    "Relevance Justification": "This evidence pertains to past claims linking Bill Clinton to Epstein\u2019s island but doesn't address the specific claim about the viral video, making it less relevant."
                }
            }
        },
        {
            "evidence3": {
                "kind": "customsearch#result",
                "title": "Jeffrey Epstein list: Fact checking false and misleading claims",
                "htmlTitle": "<b>Jeffrey</b> Epstein list: Fact checking false and misleading claims",
                "link": "https://www.usatoday.com/story/news/factcheck/2024/01/03/jeffrey-epstein-fact-check/72086418007/",
                "displayLink": "www.usatoday.com",
                "snippet": "Jan 3, 2024 ... Claim: Photo shows Trump dancing with a young girl on Jeffrey Epstein's island in 1989 ... There is no evidence that Wallace visited Jeffrey\u00a0...",
                "htmlSnippet": "Jan 3, 2024 <b>...</b> Claim: Photo shows Trump dancing with a <b>young</b> girl on <b>Jeffrey Epstein&#39;s island</b> in 1989 ... There is no <b>evidence</b> that Wallace visited Jeffrey&nbsp;...",
                "formattedUrl": "https://www.usatoday.com/story/news/factcheck/.../jeffrey.../72086418007/",
                "htmlFormattedUrl": "https://www.usatoday.com/story/news/factcheck/.../<b>jeffrey</b>.../72086418007/",
                "pagemap": {
                    "cse_thumbnail": [
                        {
                            "src": "https://encrypted-tbn0.gstatic.com/images?q=tbn:ANd9GcTGg_ncxtXGg1ZCvnUDehw8lr5iZOScMpOG17X7jJjzz9c7shGIBag50sw&s",
                            "width": "299",
                            "height": "168"
                        }
                    ],
                    "metatags": [
                        {
                            "og:image": "https://www.usatoday.com/gcdn/presto/2021/11/23/USAT/1806db36-26a2-4976-9e04-aba78d428640-ghislaine_epstein.JPG?crop=3503,1971,x0,y178&width=3200&height=1801&format=pjpg&auto=webp",
                            "apple-itunes-app": "app-id=504631398,app-argument=https://app.adjust.com/ivqo5xe",
                            "theme-color": "#0098FE",
                            "og:image:width": "3200",
                            "og:type": "article",
                            "twitter:card": "summary_large_image",
                            "twitter:title": "What's true and false about Jeffrey Epstein and the individuals on his list",
                            "og:site_name": "USA TODAY",
                            "og:title": "What's true and false about Jeffrey Epstein and the individuals on his list",
                            "og:image:height": "1801",
                            "google": "notranslate",
                            "og:description": "A roundup of claims about Jeffrey Epstein and his former girlfriend Ghislaine Maxwell.",
                            "fb:pages": "13652355666,48958576760,156345381090801,110471702456365,6566864515,137698179626815,315942225236045,927427260614748,183850168300771,1443524575938047,251228454889939,158095147555989,115535341805950,236655713446291,1621466394844549,250325640686,177037772444433,1972936962947967,2047091012096533,535551216797440",
                            "twitter:creator": "@usatoday",
                            "article:author": "Hannah Hudnall",
                            "twitter:image": "https://www.usatoday.com/gcdn/presto/2021/11/23/USAT/1806db36-26a2-4976-9e04-aba78d428640-ghislaine_epstein.JPG?crop=3503,1971,x0,y178&width=1600&height=800&format=pjpg&auto=webp",
                            "fb:app_id": "215046668549694",
                            "twitter:site": "@usatoday",
                            "viewport": "width=device-width,initial-scale=1,minimum-scale=1",
                            "twitter:description": "A roundup of claims about Jeffrey Epstein and his former girlfriend Ghislaine Maxwell.",
                            "article:content_tier": "free",
                            "og:url": "https://www.usatoday.com/story/news/factcheck/2024/01/03/jeffrey-epstein-fact-check/72086418007/",
                            "article:opinion": "false"
                        }
                    ],
                    "cse_image": [
                        {
                            "src": "https://www.usatoday.com/gcdn/presto/2021/11/23/USAT/1806db36-26a2-4976-9e04-aba78d428640-ghislaine_epstein.JPG?crop=3503,1971,x0,y178&width=3200&height=1801&format=pjpg&auto=webp"
                        }
                    ]
                },
                "website_content": {
                    "content": "Jeffrey Epstein's trial and associates have long been fruitful ground for misinformation, including baseless claims about his flight log and a bevy of altered photos wrongly linking Epstein to high-profile figures. A new crop of false claims began circulating Jan. 3 after were unsealed in U.S. District Court in New York. **More**: **More**: Here's a roundup of the latest Epstein fact checks from the USA TODAY Fact-Check Team, along with some highlights from our archive: **More from the Fact-Check Team:** | | Claims after documents were unsealed Jan. 3 ------------------------------------------- **Claim: Former President Barack Obama was with Jeffrey Epstein in a boat with a girl** _Our rating: False_ Obama was not with Epstein in the boat. The photo shows Obama with the actor George Clooney during a boat ride in Italy in June 2019. Epstein is not present in this photo. **Claim: Anderson Cooper and Kathy Griffin are named in the Jeffrey Epstein documents** _Our rating: False_ Neither Griffin nor Cooper are listed in any of the documents related to the late financier and accused sex trafficker Jeffrey Epstein. **Claim: Jeffrey Epstein documents and Anthony Weiner laptop prove Hillary Clinton visited Epstein Island 6 times** _Our rating: False_ The Epstein documents unsealed in January don't contain any proof that Clinton visited the island. She was listed as a possible witness, not accused of any wrongdoing. The emails found on former New York Rep. Anthony Weiner's laptop are unrelated and were unsealed back in 2017. **Claim: Photo shows Taylor Swift posing with Jeffrey Epstein** _Our rating: Altered_ The man shown in the photo is music executive Monte Lipman, not Jeffrey Epstein. The image was first shared in 2021, two years after Epstein died by suicide. **Claim: Oprah Winfrey, Barack Obama are among more than 160 confirmed visitors to Epstein Island** _Our ... [Content truncated]",
                    "content_tokens": 300
                },
                "website_quality_evaluation": {
                    "website_qualityScore": 7,
                    "justification": "USA Today offers a wide range of national and international news and is generally known for accuracy. However, it has sometimes been criticized for its emphasis on brevity and simplicity, which can lead to oversimplification of complex issues. Despite this, it maintains a solid reputation for news accuracy."
                },
                "ContentScore": {
                    "NewnessScore": 5,
                    "Newness Justification": "The article is from January 3, 2024, which is fairly recent but not the newest evidence available.",
                    "RelevanceScore": 4,
                    "Relevance Justification": "It indicates the absence of evidence connecting claims to Epstein's island but does not provide direct information about the video, hence, it is moderately relevant."
                }
            }
        },
        {
            "evidence4": {
                "kind": "customsearch#result",
                "title": "Jeffrey Epstein Docs Inspired These Misleading Pics and Videos To ...",
                "htmlTitle": "<b>Jeffrey</b> Epstein Docs Inspired These Misleading Pics and Videos To ...",
                "link": "https://www.snopes.com/news/2024/01/12/jeffrey-epstein-misleading-rumors/",
                "displayLink": "www.snopes.com",
                "snippet": "Jan 12, 2024 ... Rumors about Jeffrey Epstein's inner circle filled ... young girls in a house on Epstein's island. No evidence connected the video to him.",
                "htmlSnippet": "Jan 12, 2024 <b>...</b> Rumors about <b>Jeffrey Epstein&#39;s</b> inner circle filled ... <b>young girls</b> in a house on Epstein&#39;s <b>island</b>. No <b>evidence</b> connected the <b>video</b> to him.",
                "formattedUrl": "https://www.snopes.com/news/2024/01/.../jeffrey-epstein-misleading-rumor...",
                "htmlFormattedUrl": "https://www.snopes.com/news/2024/01/.../<b>jeffrey</b>-epstein-misleading-rumor...",
                "pagemap": {
                    "cse_thumbnail": [
                        {
                            "src": "https://encrypted-tbn0.gstatic.com/images?q=tbn:ANd9GcTOnqPUG1cOY7Cuf2YrQ_i2pSKqBiCUz2HD9BpOBS15y52KR-FbhahEf7y1&s",
                            "width": "300",
                            "height": "168"
                        }
                    ],
                    "metatags": [
                        {
                            "og:image": "https://mediaproxy.snopes.com/width/1200/https://media.snopes.com/2024/01/epstein_miscaptioned.png",
                            "theme-color": "#ffffff",
                            "twitter:card": "summary_large_image",
                            "article:published_time": "2024-01-13 00:39:15",
                            "og:site_name": "Snopes",
                            "apple-mobile-web-app-title": "Snopes.com",
                            "twitter:creator": "@snopes",
                            "og:description": "The unsealing of documents related to Epstein reignited rumors about his past connections to former presidents and celebrities.",
                            "twitter:image": "https://mediaproxy.snopes.com/width/1200/https://media.snopes.com/2024/01/epstein_miscaptioned.png",
                            "article:publisher": "https://www.facebook.com/snopes",
                            "twitter:site": "@snopes",
                            "article:modified_time": "2024-01-13 00:39:15",
                            "msapplication-tilecolor": "#000000",
                            "twitter:title": "Jeffrey Epstein Docs Inspired These Misleading Pics and Videos To Go Viral",
                            "og:type": "article",
                            "og:title": "Jeffrey Epstein Docs Inspired These Misleading Pics and Videos To Go Viral",
                            "fb:pages": "120680396518",
                            "article:author": "Jessica Lee",
                            "article:tag": "Donald Trump",
                            "apple-mobile-web-app-status-bar-style": "black",
                            "viewport": "width=device-width, initial-scale=1.0,minimum-scale=1.0, maximum-scale=5.0",
                            "apple-mobile-web-app-capable": "yes",
                            "mobile-web-app-capable": "yes",
                            "og:locale": "en_US",
                            "og:url": "https://www.snopes.com//news/2024/01/12/jeffrey-epstein-misleading-rumors/"
                        }
                    ],
                    "cse_image": [
                        {
                            "src": "https://mediaproxy.snopes.com/width/1200/https://media.snopes.com/2024/01/epstein_miscaptioned.png"
                        }
                    ]
                },
                "website_content": {
                    "content": "The unsealing of documents related to Epstein reignited rumors about his past connections to former presidents and celebrities. ------------------------------------------------------------------------------------------------------------------------------- ### Published Jan. 12, 2024 Rumors about Jeffrey Epstein\u2019s inner circle filled social feeds in early 2024 after a related to his sexual abuse of teenage girls. While the to what was about Epstein\u2019s offenses, they gave fodder to people eager to fictionalize the late, convicted sex offender\u2019s impact on high-profile people and evidence of his crimes. From fake photos generated by to , several misleading pieces of media circulated widely in tandem with the documents' release. Here's a sample: * . Although there are of the two together ( a \u201cterrific guy\u201d and in the recently unsealed documents), this image of them on a plane, in particular, is fake. * at a hospital recently to distract the public from the aforementioned documents. The footage was actually from 2021. ( also appeared in the newly released records.) * playing with paper airplanes while sitting in front of two collapsed Jenga towers. While the painting is real, there\u2019s no credible evidence to confirm (or disprove) Epstein owned it. * . In reality, the man is Monte Lipman, the CEO of Republic Records. * . No evidence connected the video to him. * . There were telltale signs of the photo being fake. For instance, the faces of people in the background are deformed and Trump has only one leg. Think you\u2019ve come across a fake photo or miscaptioned video involving Epstein? for potential fact-checking. Not all rumors linking Epstein to former presidents are made up. For instance, showing Trump with two of his children, Ivanka and Eric, alongside Epstein in the \u201890s is real, as well as that was taken a few years later including Melania Trump and Epstein\u2019s longtime partner, Ghislaine ... [Content truncated]",
                    "content_tokens": 300
                },
                "website_quality_evaluation": {
                    "website_qualityScore": 9,
                    "justification": "Snopes is the go-to website for debunking myths, rumors, and misinformation. It employs a rigorous process for investigating claims and is widely recognized for its accuracy and thoroughness. Snopes has solid credibility in identifying fake news and providing consumers with fact-checked information."
                },
                "ContentScore": {
                    "NewnessScore": 10,
                    "Newness Justification": "This evidence is from January 12, 2024, making it the most up-to-date source regarding claims about Epstein's activities.",
                    "RelevanceScore": 10,
                    "Relevance Justification": "Clearly states that there is no evidence connecting the video of young girls to Epstein\u2019s island, making it highly relevant to the claim in question."
                }
            }
        },
        {
            "evidence5": {
                "kind": "customsearch#result",
                "title": "Jeffrey Epstein: Prince Andrew and Bill Clinton named in court files",
                "htmlTitle": "<b>Jeffrey</b> Epstein: Prince Andrew and Bill Clinton named in court files",
                "link": "https://www.bbc.com/news/world-us-canada-67865190",
                "displayLink": "www.bbc.com",
                "snippet": "Jan 4, 2024 ... ... young, referring to girls\". The files include testimony from ... An aerial view of Jeffrey Epstein's island Little St James. The court\u00a0...",
                "htmlSnippet": "Jan 4, 2024 <b>...</b> ... <b>young</b>, referring to <b>girls</b>&quot;. The files include testimony from ... An aerial view of <b>Jeffrey Epstein&#39;s island</b> Little St James. The court&nbsp;...",
                "formattedUrl": "https://www.bbc.com/news/world-us-canada-67865190",
                "htmlFormattedUrl": "https://www.bbc.com/news/world-us-canada-67865190",
                "pagemap": {
                    "cse_thumbnail": [
                        {
                            "src": "https://encrypted-tbn0.gstatic.com/images?q=tbn:ANd9GcQcVU_lkUU3SpzqQZS68dWOp50D95qaDUKd6Lvy8csrVv0SdTEs5ZDSr0g&s",
                            "width": "300",
                            "height": "168"
                        }
                    ],
                    "metatags": [
                        {
                            "msapplication-tilecolor": "#da532c",
                            "og:image": "https://ichef.bbci.co.uk/news/1024/branded_news/A438/production/_132204024_02601dbaf451194242e19decdbdc73dc0008b2e1.png",
                            "twitter:title": "Jeffrey Epstein: Prince Andrew and Bill Clinton named in court files",
                            "twitter:card": "summary_large_image",
                            "og:image:alt": "Bill Clinton meets Jeffrey Epstein in 1993",
                            "theme-color": "#ffffff",
                            "og:title": "Jeffrey Epstein: Prince Andrew and Bill Clinton named in court files",
                            "og:description": "Files detail sex offender Jeffrey Epstein's connections but no bombshell revelations immediately emerge.",
                            "version": "2.4.1+1",
                            "twitter:image:src": "https://ichef.bbci.co.uk/news/1024/branded_news/A438/production/_132204024_02601dbaf451194242e19decdbdc73dc0008b2e1.png",
                            "next-head-count": "28",
                            "twitter:image:alt": "Bill Clinton meets Jeffrey Epstein in 1993",
                            "viewport": "width=device-width",
                            "twitter:description": "Files detail sex offender Jeffrey Epstein's connections but no bombshell revelations immediately emerge."
                        }
                    ],
                    "cse_image": [
                        {
                            "src": "https://ichef.bbci.co.uk/news/1024/branded_news/A438/production/_132204024_02601dbaf451194242e19decdbdc73dc0008b2e1.png"
                        }
                    ]
                },
                "website_content": {
                    "content": "The UK's Prince Andrew and Bill Clinton are among high-profile figures named in US court papers detailing connections of late sex offender Jeffrey Epstein. The newly released records form part of a case against Ghislaine Maxwell, Epstein's girlfriend who has been jailed for helping him abuse girls. But the documents so far unveil no major new allegations about Epstein nor revelations about his associates. Prince Andrew is accused of groping a woman, which he denies. Other names in the documents include singer Michael Jackson and magician David Copperfield, though no wrongdoing is alleged. Mr Clinton appears in a number of the documents. The former US president has acknowledged being a former associate of Epstein but has strongly denied he had any knowledge of his crimes. The first files from the much-hyped trove - covering about 900 pages - were released on Wednesday, after an order by New York Judge Loretta Preska, who acknowledged many of those named had already been identified by the media or in Maxwell's criminal trial. Judge Preska said that many others did not raise an objection to the release of the documents. However, she ordered that some names remain redacted because they would identify victims of sexual abuse. Some of the more than 100 people on the list make allegations about other individuals, or are potential witnesses, and more documents are expected to be released in the coming days. Epstein pleaded guilty to soliciting prostitution from a minor in 2009 and took his own life in 2019 while awaiting trial over sex-trafficking charges. The files include references to Johanna Sjoberg, who has claimed that Prince Andrew groped her breast while sitting on a couch inside Epstein's Manhattan apartment in 2001. Buckingham Palace has previously said her allegations are \"categorically untrue\". It has declined to comment on ... [Content truncated]",
                    "content_tokens": 300
                },
                "website_quality_evaluation": {
                    "website_qualityScore": 9,
                    "justification": "The BBC has a long-standing reputation for providing balanced and comprehensive news coverage. It follows strict editorial guidelines to maintain neutrality and truthfulness. Although it has faced criticism over perceived biases, its worldwide reach and reliability in reporting factual news still place it among the top credible news sources."
                },
                "ContentScore": {
                    "NewnessScore": 9,
                    "Newness Justification": "The source date is January 4, 2024, which is timely and relates to ongoing discussions about Epstein.",
                    "RelevanceScore": 5,
                    "Relevance Justification": "It addresses names mentioned in court files, but it doesn\u2019t specifically comment on the video being assessed, giving it a moderate relevance score."
                }
            }
        },
        {
            "evidence6": {
                "kind": "customsearch#result",
                "title": "New Videos of Billionaire Kids on Jeffrey Epstein Island Go Viral",
                "htmlTitle": "New Videos of Billionaire Kids on <b>Jeffrey</b> Epstein <b>Island</b> Go Viral",
                "link": "https://www.topview.ai/blog/detail/New-Videos-of-Billionaire-Kids-on-Jeffrey-Epstein-Island-Go-Viral",
                "displayLink": "www.topview.ai",
                "snippet": "... video indeed depicts girls on Epstein's island. To understand the ... Is there concrete evidence linking the viral video to Epstein's Island? No\u00a0...",
                "htmlSnippet": "... <b>video</b> indeed depicts <b>girls</b> on <b>Epstein&#39;s island</b>. To understand the ... Is there concrete <b>evidence linking</b> the viral <b>video</b> to <b>Epstein&#39;s Island</b>? No&nbsp;...",
                "formattedUrl": "https://www.topview.ai/.../New-Videos-of-Billionaire-Kids-on-Jeffrey-Epste...",
                "htmlFormattedUrl": "https://www.topview.ai/.../New-<b>Video</b>s-of-Billionaire-Kids-on-<b>Jeffrey</b>-Epste...",
                "pagemap": {
                    "cse_thumbnail": [
                        {
                            "src": "https://encrypted-tbn0.gstatic.com/images?q=tbn:ANd9GcTuEAlKngLRUg8KLDf1zz8ilKe3oqpFlfcLG_RsjLgJmIJ6mMZco6Vz-bg&s",
                            "width": "300",
                            "height": "168"
                        }
                    ],
                    "metatags": [
                        {
                            "og:image": "https://i.ytimg.com/vi_webp/FDrPoLts_Eg/maxresdefault.webp",
                            "og:type": "article",
                            "twitter:card": "summary_large_image",
                            "twitter:title": "New Videos of Billionaire Kids on Jeffrey Epstein Island Go Viral",
                            "viewport": "width=device-width, initial-scale=1",
                            "twitter:description": "New Videos of Billionaire Kids on Jeffrey Epstein Island Go Viral",
                            "og:title": "New Videos of Billionaire Kids on Jeffrey Epstein Island Go Viral",
                            "og:url": "https://www.topview.ai/blog/detail/New-Videos-of-Billionaire-Kids-on-Jeffrey-Epstein-Island-Go-Viral",
                            "og:description": "New Videos of Billionaire Kids on Jeffrey Epstein Island Go Viral",
                            "twitter:image": "https://i.ytimg.com/vi_webp/FDrPoLts_Eg/maxresdefault.webp"
                        }
                    ],
                    "cse_image": [
                        {
                            "src": "https://i.ytimg.com/vi_webp/FDrPoLts_Eg/maxresdefault.webp"
                        }
                    ]
                },
                "website_content": {
                    "content": "Introduction ------------ In a shocking turn of events, new videos have surfaced online claiming to show young girls inside a mysterious temple on the notorious island of Jeffrey Epstein. The billionaire, who died in prison in 2019, has been the subject of countless conspiracy theories and speculation about his involvement in a vast network of sexual exploitation. The recently released video has sparked renewed interest and outrage over the secrets and crimes that are yet to be unveiled about Little St James Island. , which was shared on various platforms, allegedly reveals young girls engaging in playful activities within the confines of Epstein's Island. The caption accompanying the video, written in Spanish, left viewers with more questions than answers, questioning what was happening and why these girls were there. However, it is important to note that there is currently no concrete evidence to support the claim that the viral video indeed depicts girls on Epstein's island. To understand the controversy surrounding this viral video, we must first revisit the dark history of Jeffrey Epstein. The wealthy financier and convicted sex offender was at the center of a high-profile scandal that rocked the world. He was arrested in 2019 on charges of sex trafficking young girls but died in jail before he could face justice. His death left many unanswered questions and fueled numerous conspiracy theories surrounding his alleged involvement with powerful individuals and his extensive criminal activities. Fast forward to early 2024, when a judge ordered the unsealing of documents in a lawsuit filed against Epstein's associate and partner in crime, Ghislaine Maxwell. These documents shed light on the extent of Epstein's activities and caused a frenzy on social media. Rumors and speculations ran rampant, and the viral video added fuel to the already burning fire. However, thorough examination and ... [Content truncated]",
                    "content_tokens": 300
                },
                "website_quality_evaluation": {
                    "website_qualityScore": 5,
                    "justification": "TopView is a newer platform that aggregates and presents content from various sources. While it offers a variety of information, the credibility and fact-checking processes behind the reporting are not as robust as those from established organizations. Caution is recommended due to the potential for misinformation from less reliable sources."
                },
                "ContentScore": {
                    "NewnessScore": 9,
                    "Newness Justification": "Published in January 2024, this article is up-to-date with current events surrounding Epstein\u2019s controversy.",
                    "RelevanceScore": 9,
                    "Relevance Justification": "Directly states there is no concrete evidence linking the viral videos to Epstein's island, making it highly relevant to verifying the claim."
                }
            }
        },
        {
            "evidence7": {
                "kind": "customsearch#result",
                "title": "New documents in the Jeffrey Epstein case detail how girls were ...",
                "htmlTitle": "New documents in the <b>Jeffrey</b> Epstein case detail how <b>girls</b> were ...",
                "link": "https://www.nbcnews.com/news/us-news/documents-jeffrey-epstein-case-released-rcna132236",
                "displayLink": "www.nbcnews.com",
                "snippet": "Jan 4, 2024 ... ... girls and young women to engage in sex acts with powerful men. ... Sjoberg said she had never met Clinton and never saw him on Epstein's private\u00a0...",
                "htmlSnippet": "Jan 4, 2024 <b>...</b> ... <b>girls</b> and <b>young</b> women to engage in sex acts with powerful men. ... Sjoberg said she had never met Clinton and never saw him on <b>Epstein&#39;s</b> private&nbsp;...",
                "formattedUrl": "https://www.nbcnews.com/.../documents-jeffrey-epstein-case-released-rcna1...",
                "htmlFormattedUrl": "https://www.nbcnews.com/.../documents-<b>jeffrey</b>-epstein-case-released-rcna1...",
                "pagemap": {
                    "cse_thumbnail": [
                        {
                            "src": "https://encrypted-tbn0.gstatic.com/images?q=tbn:ANd9GcTCMfgdFseA1RVTGV-Idi0ogvyOoP1JDbde-5afthAxlJgrXv03MXrWhh4Y&s",
                            "width": "310",
                            "height": "163"
                        }
                    ],
                    "metatags": [
                        {
                            "msapplication-config": "https://nodeassets.nbcnews.com/cdnassets/projects/ramen/favicon/nbcnews/all-other-sizes-PNG.ico/browserconfig.xml",
                            "og:image": "https://media-cldnry.s-nbcnews.com/image/upload/t_nbcnews-fp-1200-630,f_auto,q_auto:best/rockcms/2023-06/230601-jeffrey-epstein-2005-ac-547p-94aa33.jpg",
                            "og:image:width": "1200",
                            "twitter:card": "summary_large_image",
                            "og:site_name": "NBC News",
                            "branch:deeplink:title": "New documents in the Jeffrey Epstein case detail how girls were recruited to his home",
                            "og:image:type": "image/jpeg",
                            "twitter:creator": "NBCNews",
                            "og:description": "The records previously released include names of people in the late financier\u2019s orbit and depositions from women who say they were recruited for his alleged sex trafficking network.",
                            "og:image:secure_url": "https://media-cldnry.s-nbcnews.com/image/upload/t_nbcnews-fp-1200-630,f_auto,q_auto:best/rockcms/2023-06/230601-jeffrey-epstein-2005-ac-547p-94aa33.jpg",
                            "branch:deeplink:description": "The records previously released include names of people in the late financier\u2019s orbit and depositions from women who say they were recruited for his alleged sex trafficking network.",
                            "twitter:image": "https://media-cldnry.s-nbcnews.com/image/upload/t_nbcnews-fp-1024-512,f_auto,q_auto:best/rockcms/2023-06/230601-jeffrey-epstein-2005-ac-547p-94aa33.jpg",
                            "twitter:site": "@NBCNews",
                            "branch:deeplink:type": "article",
                            "og:type": "article",
                            "twitter:title": "New documents in the Jeffrey Epstein case detail how girls were recruited to his home",
                            "branch:deeplink:image": "https://media-cldnry.s-nbcnews.com/image/upload/t_nbcnews-fp-1200-630,f_auto,q_auto:best/rockcms/2023-06/230601-jeffrey-epstein-2005-ac-547p-94aa33.jpg",
                            "og:title": "New documents in the Jeffrey Epstein case detail how girls were recruited to his home",
                            "og:image:height": "630",
                            "fb:pages": "155869377766434",
                            "twitter:image:src": "https://media-cldnry.s-nbcnews.com/image/upload/t_nbcnews-fp-1024-512,f_auto,q_auto:best/rockcms/2023-06/230601-jeffrey-epstein-2005-ac-547p-94aa33.jpg",
                            "socialcopy": "More documents in Jeffrey Epstein case have been released",
                            "fb:app_id": "10150138890205613",
                            "viewport": "width=device-width, initial-scale=1, user-scalable=yes",
                            "twitter:description": "The records previously released include names of people in the late financier\u2019s orbit and depositions from women who say they were recruited for his alleged sex trafficking network.",
                            "og:locale": "en_US",
                            "og:url": "https://www.nbcnews.com/news/us-news/documents-jeffrey-epstein-case-released-rcna132236",
                            "article:opinion": "false"
                        }
                    ],
                    "cse_image": [
                        {
                            "src": "https://media-cldnry.s-nbcnews.com/image/upload/t_nbcnews-fp-1200-630,f_auto,q_auto:best/rockcms/2023-06/230601-jeffrey-epstein-2005-ac-547p-94aa33.jpg"
                        }
                    ]
                },
                "website_content": {
                    "content": "Another set of related to the late financier and convicted sex offender was released Thursday, many of them focusing on how teen girls were recruited to go to his Florida home. Some of the depositions released Thursday center on how girls were convinced to go to the home and then were asked to bring friends for additional payment. One woman who was 16 or 17 at the time said she had no massage experience and no assumption or expectation that the visit would involve sexual activity. \u201cJeffrey took my clothes off without my consent the first time I met him,\u201d according to a transcript of a deposition from the woman, whose name has been redacted. Former Palm Beach police Det. Joseph Recarey, who is now deceased, said in 2016 that Ghislaine Maxwell, , was involved in seeking girls to give massages and work at Epstein\u2019s home. Recarey said he interviewed around 33 women, according to a transcript. Only two, who were older, had any massage experience, he said. Most of the girls were younger than 18. \"Each of the victims that went to the home were asked to bring their friends to the home. Some complied and some didn\u2019t,\" Recarey said. The descriptions of how women were recruited contained in the documents is consistent with what was testified to at Maxwell\u2019s criminal trial. Nineteen exhibits totaling 327 pages of previously sealed documents were released Thursday by a federal court in New York. The disclosure is part of a settled lawsuit first filed in 2015 against British socialite and Epstein confidant by , who said she was a victim of sex trafficking and abuse when she was a teenager in the early 2000s. In total, the hundreds of pages of unsealed documents \u2014 which are the latest to attract in the ... [Content truncated]",
                    "content_tokens": 300
                },
                "website_quality_evaluation": {
                    "website_qualityScore": 8,
                    "justification": "NBC News is a major news organization with a long history in investigative journalism and news coverage. While it generally provides reliable reporting, it has occasionally been accused of bias, especially concerning political coverage. However, its commitment to fact-checking and journalistic integrity ranks it highly."
                },
                "ContentScore": {
                    "NewnessScore": 8,
                    "Newness Justification": "This article is from January 4, 2024, making it a relatively recent source.",
                    "RelevanceScore": 5,
                    "Relevance Justification": "Discusses documents from the Epstein case and allegations related to young women, but does not specifically address the claim about the video, resulting in moderate relevance."
                }
            }
        },
        {
            "evidence8": {
                "kind": "customsearch#result",
                "title": "Did your opinion of Trump change when you found out he went to ...",
                "htmlTitle": "Did your opinion of Trump change when you found out he went to ...",
                "link": "https://www.quora.com/Did-your-opinion-of-Trump-change-when-you-found-out-he-went-to-Epsteins-Island-7-times-on-Epsteins-jet",
                "displayLink": "www.quora.com",
                "snippet": "Jan 15, 2024 ... I read in comments that there is evidence that Bill Clinton visited Epstein's island. ... Jeffrey Epstein's travel manifests to Pedo Island?",
                "htmlSnippet": "Jan 15, 2024 <b>...</b> I read in comments that there is <b>evidence</b> that Bill Clinton visited Epstein&#39;s <b>island</b>. ... <b>Jeffrey Epstein&#39;s</b> travel manifests to Pedo <b>Island</b>?",
                "formattedUrl": "https://www.quora.com/Did-your-opinion-of-Trump-change-when-you-fo...",
                "htmlFormattedUrl": "https://www.quora.com/Did-your-opinion-of-Trump-change-when-you-fo...",
                "pagemap": {
                    "metatags": [
                        {
                            "al:android:url": "intent://www.quora.com/Did-your-opinion-of-Trump-change-when-you-found-out-he-went-to-Epsteins-Island-7-times-on-Epsteins-jet#Intent;scheme=qhttp;package=com.quora.android;S.market_referrer=launch_url=https%3A%2F%2Fwww.quora.com%2FDid-your-opinion-of-Trump-change-when-you-found-out-he-went-to-Epsteins-Island-7-times-on-Epsteins-jet&logging_data=uid%3DNone;end",
                            "theme-color": "#b92b27",
                            "viewport": "initial-scale=1, maximum-scale=1, user-scalable=no, width=device-width, minimum-scale=1, viewport-fit=cover",
                            "al:android:package": "com.quora.android",
                            "fb:pages": "255232486973",
                            "twitter:widgets:theme": "light"
                        }
                    ],
                    "QAPage": [
                        {}
                    ]
                },
                "website_content": {
                    "content": "Did your opinion of Trump change when you found out he went to Epstein's Island 7 times on Epstein's jet? - Quora =============== Something went wrong. Wait a moment and try again. Try again Skip to content Skip to search Sign In Did your opinion of Trump change when you found out he went to Epstein's Island 7 times on Epstein's jet? All related (40) Sort Recommended ] Studied Production Management & Management (Graduated 1992) \u00b7 Author has 12.9K answers and 68.1M answer views \u00b7 There is absolutely nothing that would make me think any less of Trump. I have hit my rock bottom with him. Evidently, his rock bottom has multiple sub-basements. Upvote \u00b7 999371 96 Related questions More answers below ] Retired (2015\u2013present) \u00b7 Author has 2.9K answers and 504.3K answer views \u00b7 No, he's a pig. No surprise there. Upvote \u00b7 98 ] Author has 6.3K answers and 508.9K answer views \u00b7 That's old news. Along with his public lusting after his own teenage daughter, his unannounced entry into the dressing rooms of teenage pageant contestants, and his penchant for \u201cgrabbing women by the pu\\*\\*y\u201d. Anyone who's paid attention has known, for years, that he's a pedophile and a pervert. VOTE BLUE \ud83d\udc99 Upvote \u00b7 94 91 ] Author has 597 answers and 21.4K answer views \u00b7 Nope. I already knew he was garbage. Cheated on every wife and girlfriend he has ever had. Slimey trashy behaviors. Upvote \u00b7 94 Related questions Related questions Advertisement \u00b7 \u00b7 \u00b7 \u00b7 \u00b7 \u00b7 \u00b7 \u00b7 \u00a9 Quora, Inc. 2024 ... [Content truncated]",
                    "content_tokens": 300
                },
                "website_quality_evaluation": {
                    "website_qualityScore": 4,
                    "justification": "Quora is a platform for crowdsourced questions and answers and lacks a professional editorial process. The quality and reliability of information depend heavily on individual contributors, which can result in varying levels of accuracy. It is best used as a supplementary source rather than a primary news source due to potential misinformation."
                },
                "ContentScore": {
                    "NewnessScore": 4,
                    "Newness Justification": "The article is from January 15, 2024, so it\u2019s relatively recent, but it is more anecdotal and lacks substantial new insights on Epstein.",
                    "RelevanceScore": 2,
                    "Relevance Justification": "This is a general inquiry about perceptions of Epstein and does not provide relevant information about the claims concerning the video."
                }
            }
        },
        {
            "evidence9": {
                "kind": "customsearch#result",
                "title": "Case 18-2868, Document 280, 08/09/2019, 2628232, Page1 of 74",
                "htmlTitle": "Case 18-2868, Document 280, 08/09/2019, 2628232, Page1 of 74",
                "link": "https://www.courthousenews.com/wp-content/uploads/2019/08/Giuffre-unseal.pdf",
                "displayLink": "www.courthousenews.com",
                "snippet": "Aug 9, 2019 ... Epstein's household was not to recruit girls and young women for Jeffrey Epstein. ... evidence clearly linking Defendant to Epstein's\u00a0...",
                "htmlSnippet": "Aug 9, 2019 <b>...</b> <b>Epstein&#39;s</b> household was not to recruit <b>girls</b> and <b>young</b> women for <b>Jeffrey</b> Epstein. ... <b>evidence</b> clearly <b>linking</b> Defendant to <b>Epstein&#39;s</b>&nbsp;...",
                "formattedUrl": "https://www.courthousenews.com/wp-content/uploads/.../Giuffre-unseal.pdf",
                "htmlFormattedUrl": "https://www.courthousenews.com/wp-content/uploads/.../Giuffre-unseal.pdf",
                "pagemap": {
                    "metatags": [
                        {
                            "moddate": "D:20190809093036-04'00'",
                            "creationdate": "D:20190717183207-04'00'",
                            "producer": "PDFTron PDFNet; modified using iText\u00ae 5.5.9 \u00a92000-2015 iText Group NV (AGPL-version)"
                        }
                    ]
                },
                "mime": "application/pdf",
                "fileFormat": "PDF/Adobe Acrobat",
                "website_content": {
                    "content": "# United States District Court Southern District of New York Virginia L. Giuffre, Plaintiff, Case No.: 15-cv-07433-RWS v. Ghislaine Maxwell, Defendant. ________________________________/ PLAINTIFFS\u2019 RESPONSE TO DEFENDANT\u2019S MOTION FOR SUMMARY JUDGMENT Sigrid McCawley BOIES, SCHILLER & FLEXNER LLP 401 E. Las Olas Blvd., Suite 1200 Ft. Lauderdale, FL 33301 (954) 356-0011 Case 18-2868, Document 280, 08/09/2019, 2628232, Page1 of 74 i TABLE OF CONTENTS Page I. PRELIMINARY STATEMENT .........................................................................................1 II. UNDISPUTED FACTS.......................................................................................................4 A. It is an Undisputed Fact That Multiple Witnesses Deposed in This Case Have Testified That Defendant Operated as Convicted Pedophile Jeffrey Epstein\u2019s Procurer of Underage Girls......................................................................................4 1. It is an undisputed fact that Joanna Sjoberg testified Defendant lured her from her school to have sex with Epstein under the guise of hiring her for a job answering phones....................................................................4 2. It is an undisputed fact that Tony Figueroa testified that Defendant would call him to bring over underage girls and that Defendant and Epstein would have threesomes with Ms. Giuffre.......................................6 3. It is an undisputed fact that Rinaldo Rizzo testified that Defendant took the passport of a 15-year-old Swedish girl and threatened her when she refused to have sex with Epstein. ................................................8 4. It is an undisputed fact that Lyn Miller testified that she believed Defendant became Ms. Giuffre\u2019s \u201cnew mama\u201d...........................................9 5. It is an undisputed Fact that Detective Joseph Recarey testified that he sought to investigate Defendant in relation to his investigation of Jeffrey Epstein. ............................................................................................9 6. It is an undisputed fact that Pilot David Rodgers testified that he flew Defendant and Ms. Giuffre at least 23 times on Epstein\u2019s jet, the \u201cLolita Express\u201d and that \u201cGM\u201d on the flight logs Stands for Ghislaine Maxwell.....................................................................................................10 7. It is an undisputed fact that Sarah Kellen, Nadia Marcinkova, and Jeffrey Epstein invoked the fifth amendment when asked about Defendant trafficking ... [Content truncated]",
                    "content_tokens": 300
                },
                "website_quality_evaluation": {
                    "website_qualityScore": 6,
                    "justification": "Courthouse News specializes in legal news and reporting on court cases. While it provides unique insights into the legal world, it may not cover a wide range of general news topics. Its credibility is generally stronger in legal reporting, but it might not be as reliable in non-legal news areas."
                },
                "ContentScore": {
                    "NewnessScore": 3,
                    "Newness Justification": "This document is quite old, dating back to August 2019, which makes it the oldest in this context.",
                    "RelevanceScore": 4,
                    "Relevance Justification": "It covers Epstein's household operations but does not help verify the specific claim about the video, resulting in low relevance."
                }
            }
        }
    ]
}